{"transcript":"anaˈlyːzə","exists":true,"definitions":["Systematische Untersuchung eines Objekts oder Sachverhalts in seine Bestandteile.","Auswertung von Daten oder Proben.","Psychoanalytische Behandlung."],"examples":["Die chemische Analyse.","Eine genaue Analyse der Daten.","Er ist seit Jahren in Analyse."],"lemma":"Analyse","lemmaPos":"noun","synonyms":["Untersuchung","Auswertung","Zergliederung","Exploration"],"number":"singular","pluralForm":"die Analysen","gender":"feminine","source":"Analyse"}