{"transcript":"Υàha äΧ·ptΥ¨z…¦tΆΓs…ô","exists":true,"definitions":["Grammatik: ein Satz, der syntaktisch vollstΟΛndig ist und nicht von einem anderen Satz abhΟΛngt.","Philosophie: grundlegende, nicht weiter ableitbare Aussagen oder Prinzipien."],"examples":["Die HauptsΟΛtze der Thermodynamik sind fundamental.","Ein Text besteht oft aus mehreren HauptsΟΛtzen.","Er formulierte die HauptsΟΛtze klar und prΟΛgnant."],"lemma":"Hauptsatz","lemmaPos":"noun","synonyms":["Kernsatz","Grundsatz","Prinzip"],"number":"plural","pluralForm":"die HauptsΟΛtze","source":"HauptsΟΛtze"}