{"transcript":"ﾋ位穫tﾉ斥恵ﾊ‖ﾉｪﾌｯtnﾌｩ","exists":true,"definitions":["jemandem etwas zur Prﾃｼfung, Entscheidung oder Kenntnisnahme vorlegen","einen Vorschlag oder ein Angebot machen"],"examples":["Ich werde Ihnen einen Vorschlag unterbreiten.","Die Firma unterbreitete ein attraktives Angebot.","Er unterbreitete seine Ideen dem Vorstand."],"lemma":"unterbreiten","lemmaPos":"verb","synonyms":["vorlegen","vorschlagen","anbieten","prﾃ､sentieren"],"number":"plural","tense":"present","pastTenses":"unterbreitete, hat unterbreitet","presentTenses":"ich unterbreite, du unterbreitest, er/sie/es unterbreitet","isIrregular":false,"source":"unterbreiten"}