{"transcript":"ˈaʊ̯fˌfyːʁən","exists":true,"definitions":["etwas auf einer Bühne oder vor Publikum darbieten","etwas in einer Liste oder Aufstellung nennen","sich auf eine bestimmte Weise verhalten"],"examples":["Die Kinder führen ein Theaterstück auf.","Er führte alle Ausgaben detailliert auf.","Sie führte sich sehr unhöflich auf."],"lemma":"aufführen","lemmaPos":"verb","synonyms":["darbieten","auflisten","benehmen"],"number":"other","pastTenses":"führte auf, hat aufgeführt","tense":"present","source":"aufführen"}