{"transcript":"ˈɡlaɪçɡəˌzɪntə","exists":true,"definitions":["Person, die die gleichen Ansichten, Interessen oder Überzeugungen hat wie man selbst.","Jemand, der ähnliche Gedanken oder Gefühle teilt."],"examples":["Sie fand schnell Gleichgesinnte.","Unter Gleichgesinnten fühlt man sich wohl.","Die Gruppe bestand nur aus Gleichgesinnten."],"lemma":"Gleichgesinnte","lemmaPos":"noun","synonyms":["Gesinnungsgenosse","Seelenverwandter","Gleichdenkende"],"number":"plural","pluralForm":"die Gleichgesinnten","source":"Gleichgesinnte"}