{"transcript":"ňątsuňźňĆliňźf…źn","exists":true,"definitions":["etwas zus√§tzlich liefern","als Zulieferer t√§tig sein","Material oder Teile an ein anderes Unternehmen liefern"],"examples":["Die Firma muss die fehlenden Teile zuliefern.","Wir zuliefern seit Jahren Komponenten f√ľr die Automobilindustrie.","Er wird die restlichen Dokumente zuliefern."],"lemma":"zuliefern","lemmaPos":"verb","synonyms":["beliefern","liefern","bereitstellen"],"number":"singular","tense":"present","pastTenses":"lieferte zu, hat zugeliefert","presentTenses":"ich liefere zu, du lieferst zu, er/sie/es liefert zu","isIrregular":false,"source":"zuliefern"}