{"transcript":"fﾉ嵋昔ｯﾋ位【ﾋ惜昔ｯt","exists":true,"definitions":["mischt oder rﾃｼhrt etwas grﾃｼndlich um, sodass es eine homogene Masse bildet","hat etwas durch Rﾃｼhren vermischt"],"examples":["Sie verrﾃｼhrt die Eier mit der Milch.","Der Koch verrﾃｼhrt die Soﾃ歹.","Er hat die Zutaten gut verrﾃｼhrt."],"lemma":"verrﾃｼhren","lemmaPos":"verb","synonyms":["vermischen","umrﾃｼhren","mixen"],"number":"singular","tense":"present","pastTenses":"verrﾃｼhrte, hat verrﾃｼhrt","presentTenses":"ich verrﾃｼhre, du verrﾃｼhrst, er/sie/es verrﾃｼhrt","isIrregular":false,"source":"verrﾃｼhrt"}