{"transcript":"ɡəˈʔɛʁɡɐt","exists":true,"definitions":["Verärgert sein oder werden","Jemanden verärgern oder reizen","Sich über etwas ärgern"],"examples":["Er hat sich über die Verspätung geärgert.","Sie hat ihn mit ihren Kommentaren geärgert.","Ich habe mich gestern sehr geärgert."],"lemma":"ärgern","lemmaPos":"verb","synonyms":["verärgert","gereizt","verstimmt"],"number":"singular","tense":"past","pastTenses":"hat geärgert, ist geärgert worden","presentTenses":"ich ärgere, du ärgerst, er/sie/es ärgert","isIrregular":false,"source":"geärgert"}