{"transcript":"fﾉ嵋昔ｯﾋ埿ﾍ｡sﾃｸﾋ惜｡ﾉ腎","exists":true,"definitions":["macht langsamer oder spﾃ､ter","verschiebt auf einen spﾃ､teren Zeitpunkt","bewirkt eine Verzﾃｶgerung"],"examples":["Der Zug verzﾃｶgert sich.","Er verzﾃｶgert die Entscheidung.","Die Lieferung verzﾃｶgert sich um einen Tag."],"lemma":"verzﾃｶgern","lemmaPos":"verb","synonyms":["aufschieben","verlangsamen","hinauszﾃｶgern"],"number":"singular","tense":"present","pastTenses":"verzﾃｶgerte, hat verzﾃｶgert","presentTenses":"ich verzﾃｶgere, du verzﾃｶgerst, er/sie/es verzﾃｶgert","isIrregular":false,"source":"verzﾃｶgert"}