{"transcript":"ﾋ𡈽ﾉｪnﾊネﾊ郭","exists":true,"definitions":["Das Einschlieﾃ歹n oder Eingeschlossensein von etwas.","Eine Substanz, die in einer anderen Substanz eingeschlossen ist.","Die Aufnahme in eine Gruppe oder einen Bereich."],"examples":["Der Einschluss von Gasblasen im Material.","Der Einschluss in die Untersuchung.","Der Einschluss von Fremdkﾃｶrpern."],"lemma":"Einschluss","lemmaPos":"noun","synonyms":["Inklusion","Einschlieﾃ殷ng","Eingliederung"],"number":"singular","pluralForm":"die Einschlﾃｼsse","gender":"masculine","source":"Einschluss"}