{"transcript":"ˈvɪtsfiˌɡuːɐ̯","exists":true,"definitions":["Eine Person, die durch ihr lächerliches Verhalten oder Aussehen nicht ernst genommen wird.","Eine komische Gestalt in einer Erzählung oder einem Witz."],"examples":["Er machte sich zur Witzfigur.","Niemand respektiert diese Witzfigur.","In dem Film spielt er eine totale Witzfigur."],"lemma":"Witzfigur","lemmaPos":"noun","synonyms":["Lachnummer","Witzbold","Witzblattfigur","Witzgestalt"],"number":"singular","pluralForm":"die Witzfiguren","gender":"feminine","source":"Witzfigur"}