{"transcript":"foːɐ̯ˈbaɪ̯t͡suˌkɔmən","exists":true,"definitions":["An einem Ort oder einer Person vorbeigehen oder -fahren.","Jemanden besuchen oder aufsuchen.","Eine Schwierigkeit oder ein Hindernis überwinden."],"examples":["Es ist schwer, an ihm vorbeizukommen.","Ich muss morgen bei dir vorbeizukommen.","Wir müssen einen Weg finden, an diesem Problem vorbeizukommen."],"lemma":"vorbeikommen","lemmaPos":"verb","synonyms":["passieren","besuchen","überwinden"],"number":"singular","pastTenses":"kam vorbei, ist vorbeigekommen","tense":"present","source":"vorbeizukommen"}