{"transcript":"kamˈpanjə","exists":true,"definitions":["Eine zeitlich begrenzte Aktion mit einem bestimmten Ziel.","Großangelegte Werbe- oder Aufklärungsaktion.","Militärischer Feldzug."],"examples":["Die neue Werbekampagne startet morgen.","Eine Kampagne gegen das Rauchen.","Die politische Kampagne war erfolgreich."],"lemma":"Kampagne","lemmaPos":"noun","synonyms":["Aktion","Feldzug","Offensive","Werbeaktion"],"number":"singular","pluralForm":"die Kampagnen","gender":"feminine","source":"Kampagne"}