{"transcript":"fɛɐ̯ˈʃɔɪ̯çt","exists":true,"definitions":["hat jemanden oder etwas durch Schreien, Drohen oder Ähnliches vertrieben","hat jemanden oder etwas verjagt"],"examples":["Der Hund hat die Katze verscheucht.","Die laute Musik hat die Vögel verscheucht.","Er hat die Kinder vom Spielplatz verscheucht."],"lemma":"verscheuchen","lemmaPos":"verb","synonyms":["verjagen","vertreiben","verschrecken"],"number":"singular","tense":"past","pastTenses":"verscheuchte, hat verscheucht","presentTenses":"ich verscheuche, du verscheuchst, er/sie/es verscheucht","isIrregular":false,"source":"verscheucht"}