{"transcript":"藞a蕣摊f藢蕘e藧伞蕣艐","exists":true,"definitions":["Zustand der Erregung oder Beunruhigung","Emotionale Erregung, oft verbunden mit Nervosit盲t oder Unruhe"],"examples":["Die Aufregung vor dem Auftritt war gro脽.","Es gab viel Aufregung um die neue Regelung.","Sie konnte ihre Aufregung kaum verbergen."],"lemma":"Aufregung","lemmaPos":"noun","synonyms":["Erregung","Beunruhigung","Nervosit盲t","Unruhe"],"number":"singular","pluralForm":"die Aufregungen","gender":"feminine","source":"Aufregung"}