{"transcript":"藞ta瑟l藢ne藧m蓹蕘瑟n","exists":true,"definitions":["Eine weibliche Person, die an etwas teilnimmt.","Weibliche Person, die bei einer Veranstaltung, einem Kurs oder Wettbewerb mitmacht."],"examples":["Die Teilnehmerin hat den ersten Preis gewonnen.","Jede Teilnehmerin erhielt ein Zertifikat.","Die Anzahl der Teilnehmerinnen ist begrenzt."],"lemma":"teilnehmen","lemmaPos":"verb","synonyms":["Mitwirkende","Beteiligte","Akteurin"],"number":"singular","pluralForm":"die Teilnehmerinnen","gender":"feminine","source":"Teilnehmerin"}