{"transcript":"fﾉ嵋昔ｯﾋ伊｡ﾅ鍍ﾉ刃","exists":true,"definitions":["Jemanden oder etwas ﾃｼbermﾃ､ﾃ殃g verehren oder anbeten.","Jemanden oder etwas als Gott oder gﾃｶttlich betrachten."],"examples":["Sie vergﾃｶttert ihren Mann.","Er vergﾃｶttert seine Kinder.","Manche Fans vergﾃｶttern ihre Idole."],"lemma":"vergﾃｶttern","lemmaPos":"verb","synonyms":["anbeten","verehren","bewundern","adorieren"],"number":"singular","tense":"present","pastTenses":"vergﾃｶtterte, hat vergﾃｶttert","presentTenses":"ich vergﾃｶttere, du vergﾃｶtterst, er/sie/es vergﾃｶttert","isIrregular":false,"source":"vergﾃｶttern"}