{"transcript":"ﾋ圡aﾉｪﾌｯﾋ計aﾋ惜｡nﾌｩ","exists":true,"definitions":["Ein an ein Motorrad angebauter Seitenwagen.","Ein zusﾃ､tzlicher Wagen, der an einen Zug oder eine Straﾃ歹nbahn angehﾃ､ngt wird."],"examples":["Das Motorrad mit Beiwagen fuhr schnell.","Der Beiwagen wurde an die Lokomotive gekoppelt.","Sie reisten im Beiwagen durch die Landschaft."],"lemma":"Beiwagen","lemmaPos":"noun","synonyms":["Seitenwagen","Anhﾃ､nger"],"number":"singular","pluralForm":"die Beiwagen","gender":"masculine","source":"Beiwagen"}