{"transcript":"ΥàlaΥêd…ôkapatsit…¦Υêt","exists":true,"definitions":["Die maximale Menge an Ladung, die ein Transportmittel aufnehmen kann.","Das FassungsvermΟΕgen eines Speichers oder einer Batterie."],"examples":["Die LadekapazitΟΛt des Schiffes ist begrenzt.","Die LadekapazitΟΛt des Akkus reicht fΟΦr einen Tag.","Wir mΟΦssen die LadekapazitΟΛt der Drohne erhΟΕhen."],"lemma":"LadekapazitΟΛt","lemmaPos":"noun","synonyms":["LadevermΟΕgen","TragfΟΛhigkeit","FassungsvermΟΕgen"],"number":"singular","pluralForm":"die LadekapazitΟΛten","gender":"feminine","source":"LadekapazitΟΛt"}