{"transcript":"ˈaʊ̯sˌtʁeːtn̩","exists":true,"definitions":["aus etwas heraustreten, sich entfernen","aus einer Organisation, Partei o. Ä. austreten","Urin oder Kot ausscheiden","einen Brand, eine Glut durch Treten löschen","einen Pfad, Weg durch häufiges Begehen sichtbar machen"],"examples":["Er wird aus dem Verein austreten.","Bitte treten Sie nicht auf den Rasen aus.","Das Pferd muss austreten.","Sie hat die Zigarette ausgetreten.","Der Weg ist schon ausgetreten."],"lemma":"austreten","lemmaPos":"verb","synonyms":["verlassen","ausscheiden","löschen"],"number":"other","pastTenses":"trat aus, ist ausgetreten","tense":"present","source":"austreten"}