{"transcript":"zɪç ˈantsiːən","exists":true,"definitions":["Kleidung anlegen","sich kleiden","attraktiv wirken, anziehend sein"],"examples":["Er muss sich noch anziehen.","Zieh dich warm an!","Die neue Mode zieht sich gut an.","Diese Geschichte zieht sich gut an."],"lemma":"sich anziehen","lemmaPos":"verb","synonyms":["sich ankleiden","sich kleiden"],"number":"singular","tense":"present","pastTenses":"zog sich an, hat sich angezogen","presentTenses":"ich ziehe mich an, du ziehst dich an, er/sie/es zieht sich an","isIrregular":true,"source":"sich anziehen"}