{"transcript":"ˌadministriːrən","exists":true,"definitions":["verwalten, leiten, regeln","eine Dosis verabreichen (Medizin)"],"examples":["Die Regierung muss das Land administrieren.","Der Arzt wird das Medikament administrieren."],"lemma":"administrieren","lemmaPos":"verb","synonyms":["verwalten","leiten","regieren","verabreichen"],"number":"singular","tense":"present","pastTenses":"administrierte, hat administriert","presentTenses":"ich administriere, du administrierst, er/sie/es administriert","isIrregular":false,"source":"administrieren"}