{"transcript":"틛툮t톩l틟툮te틣t","exists":true,"definitions":["Bleibt in einer Position ohne Bewegung","Kommt zum Stillstand","H칬rt auf sich zu bewegen oder zu funktionieren"],"examples":["Die Zeit stillsteht, wenn ich bei dir bin.","Der Motor stillsteht, wenn kein Benzin mehr da ist.","Das Herz stillsteht, wenn es aufh칬rt zu schlagen."],"lemma":"stillstehen","lemmaPos":"verb","synonyms":["anhalten","stehenbleiben","stocken"],"number":"singular","tense":"present","pastTenses":"stand still, ist stillgestanden","presentTenses":"ich stehe still, du stehst still, er/sie/es steht still","isIrregular":true,"source":"stillsteht"}