{"transcript":"ˈʀaʊ̯sˌfɪndn̩","exists":true,"definitions":["etwas durch Nachforschen oder Überlegen entdecken","einen Weg nach draußen finden","eine Lösung für ein Problem finden"],"examples":["Ich muss rausfinden, wie das funktioniert.","Wir konnten den Ausgang nicht rausfinden.","Sie hat rausgefunden, wer der Täter war."],"lemma":"rausfinden","lemmaPos":"verb","synonyms":["herausfinden","entdecken","ermitteln","erfahren"],"number":"singular","pastTenses":"fand raus, hat rausgefunden","tense":"present","source":"rausfinden"}