{"transcript":"ﾉｪn.jﾉｪﾋ埿ﾍ｡siﾋ惜昔ｯt","exists":true,"definitions":["fﾃｼhrt eine Flﾃｼssigkeit in einen Kﾃｶrper oder ein System ein","verabreicht eine Injektion"],"examples":["Der Arzt injiziert das Medikament.","Die Krankenschwester injiziert den Impfstoff.","Man injiziert die Substanz direkt in den Muskel."],"lemma":"injizieren","lemmaPos":"verb","synonyms":["einspritzen","verabreichen","spritzen"],"number":"singular","tense":"present","pastTenses":"injizierte, hat injiziert","presentTenses":"ich injiziere, du injizierst, er/sie/es injiziert","isIrregular":false,"source":"injiziert"}