{"transcript":"aʊ̯sˈaɪ̯nandɐˌneːmən","exists":true,"definitions":["in Einzelteile zerlegen","kritisieren, analysieren","jemanden scharf zurechtweisen"],"examples":["Er wird das Gerät auseinandernehmen.","Sie hat seine Argumente auseinandergenommen.","Der Chef hat ihn auseinandergenommen."],"lemma":"auseinandernehmen","lemmaPos":"verb","synonyms":["zerlegen","demontieren","kritisieren","analysieren"],"number":"singular","pastTenses":"nahm auseinander, hat auseinandergenommen","tense":"present","source":"auseinandernehmen"}