{"transcript":"ˈvaɪtɐɡəˌlaɪtət","exists":true,"definitions":["an einen anderen Ort oder eine andere Person gesendet","übermittelt oder weitergeleitet","in eine andere Richtung gelenkt"],"examples":["Die E-Mail wurde erfolgreich weitergeleitet.","Der Anruf wird an die Zentrale weitergeleitet.","Informationen wurden an das Team weitergeleitet."],"lemma":"weiterleiten","lemmaPos":"verb","synonyms":["übermitteln","senden","leiten","schicken"],"number":"singular","pastTenses":"leitete weiter, hat weitergeleitet","tense":"past","source":"weitergeleitet"}