{"transcript":"ˈaɪ̯nˌʃɛŋkn̩","exists":true,"definitions":["Flüssigkeit in ein Gefäß füllen","Getränke in Gläser oder Tassen füllen"],"examples":["Er schenkt den Wein ein.","Kannst du mir bitte Kaffee einschenken?","Sie hat das Wasser in die Karaffe eingeschenkt."],"lemma":"einschenken","lemmaPos":"verb","synonyms":["eingießen","füllen","servieren"],"number":"singular","tense":"present","pastTenses":"schenkte ein, hat eingeschenkt","presentTenses":"ich schenke ein, du schenkst ein, er/sie/es schenkt ein","isIrregular":false,"source":"einschenken"}