{"transcript":"liːkst","exists":true,"definitions":["Befindest dich in einer liegenden Position","Befindest dich an einem bestimmten Ort (umgangssprachlich)","Ist die Ursache oder der Grund für etwas (umgangssprachlich)"],"examples":["Du liegst im Bett.","Die Stadt liegt am Fluss.","Woran liegst, dass es nicht funktioniert?"],"lemma":"liegen","lemmaPos":"verb","synonyms":["ruhst","befindest","verweilst"],"number":"singular","tense":"present","pastTenses":"lagst, hast gelegen","presentTenses":"ich liege, du liegst, er/sie/es liegt","isIrregular":true,"source":"liegst"}