{"transcript":"telefoˈniːʁən","exists":true,"definitions":["Eine telefonische Verbindung herstellen und sprechen.","Ein Telefongespräch führen."],"examples":["Ich muss noch telefonieren.","Wir haben lange telefoniert.","Kannst du bitte telefonieren?"],"lemma":"telefonieren","lemmaPos":"verb","synonyms":["anrufen","durchrufen","fernsprechen"],"number":"singular","tense":"present","pastTenses":"telefonierte, hat telefoniert","presentTenses":"ich telefoniere, du telefonierst, er/sie/es telefoniert","isIrregular":false,"source":"telefonieren"}