{"transcript":"ɛˈʁeːɡn̩","exists":true,"definitions":["jemanden emotional oder sexuell stimulieren","Aufmerksamkeit oder Interesse hervorrufen","eine Reaktion oder einen Zustand auslösen"],"examples":["Die Nachricht erregte großes Aufsehen.","Seine Rede erregte die Gemüter.","Das Bild erregte seine Neugier."],"lemma":"erregen","lemmaPos":"verb","synonyms":["aufregen","begeistern","stimulieren","provozieren"],"number":"plural","tense":"present","pastTenses":"erregte, hat erregt","presentTenses":"ich errege, du erregst, er/sie/es erregt","isIrregular":false,"source":"erregen"}