{"transcript":"tﾍ｡suﾋ位￢縮ﾋ荊ﾍ｡saﾋ人ﾉ冢","exists":true,"definitions":["Geld oder Schulden zurﾃｼckgeben","Eine Schuld begleichen","Eine Rﾃｼckzahlung leisten"],"examples":["Ich muss das Darlehen zurﾃｼckzahlen.","Er hat die Schulden pﾃｼnktlich zurﾃｼckgezahlt.","Wir werden den Betrag in Raten zurﾃｼckzahlen."],"lemma":"zurﾃｼckzahlen","lemmaPos":"verb","synonyms":["erstatten","begleichen","rﾃｼckvergﾃｼten"],"number":"other","tense":"present","pastTenses":"zahlte zurﾃｼck, hat zurﾃｼckgezahlt","presentTenses":"ich zahle zurﾃｼck, du zahlst zurﾃｼck, er/sie/es zahlt zurﾃｼck","isIrregular":false,"source":"zurﾃｼckzahlen"}