{"transcript":"ˈdeːnən","exists":true,"definitions":["Etwas länger oder größer machen, indem man daran zieht.","Muskeln durch bestimmte Übungen flexibler machen.","Eine Zeitspanne oder einen Vorgang ausweiten."],"examples":["Den Teig dehnen.","Die Muskeln dehnen.","Die Besprechung dehnen."],"lemma":"dehnen","lemmaPos":"verb","synonyms":["strecken","ausweiten","verlängern"],"number":"plural","tense":"present","pastTenses":"dehnte, hat gedehnt","presentTenses":"ich dehne, du dehnst, er/sie/es dehnt","isIrregular":false,"source":"dehnen"}