{"transcript":"ˈʃtɛktn̩","exists":true,"definitions":["befanden sich (in etwas)","wurden (in etwas) gesteckt","hielten sich auf (an einem Ort)"],"examples":["Die Schlüssel steckten im Schloss.","Sie steckten die Blumen in die Vase.","Die Kinder steckten voller Energie."],"lemma":"stecken","lemmaPos":"verb","synonyms":["stecken","befinden","hineintun"],"number":"plural","tense":"past","pastTenses":"steckten, haben gesteckt","presentTenses":"ich stecke, du steckst, er/sie/es steckt","isIrregular":false,"source":"steckten"}