{"transcript":"dﾉｪ ﾋ位￢縮kﾋ憩ﾋ惜昔ｯ","exists":true,"definitions":["Der Vorgang des Zurﾃｼckkommens an einen Ort oder in einen Zustand.","Die Wiederaufnahme einer frﾃｼheren Position oder Aktivitﾃ､t."],"examples":["Die Rﾃｼckkehr nach Hause war lang erwartet.","Er plante seine Rﾃｼckkehr in die Politik.","Die Rﾃｼckkehr zur Normalitﾃ､t dauerte."],"lemma":"Rﾃｼckkehr","lemmaPos":"noun","synonyms":["Heimkehr","Wiederkehr","Zurﾃｼckkunft"],"number":"singular","pluralForm":"die Rﾃｼckkehren","gender":"feminine","source":"die Rﾃｼckkehr"}