{"transcript":"ɛɐˈhɛŋən","exists":true,"definitions":["Jemanden oder sich selbst durch Erhängen töten.","Etwas an einem Seil oder einer Schlinge aufhängen, um es zu töten oder zu bestrafen."],"examples":["Der Mann wurde erhängt.","Er drohte, sich zu erhängen.","Sie wollten den Verräter erhängen."],"lemma":"erhängen","lemmaPos":"verb","synonyms":["aufhängen","henken"],"number":"singular","tense":"present","pastTenses":"erhängte, hat erhängt","presentTenses":"ich erhänge, du erhängst, er/sie/es erhängt","isIrregular":false,"source":"erhängen"}