{"transcript":"틛p톖투t톛mone틣","exists":true,"definitions":["Eine kleine Tasche zur Aufbewahrung von Geldm칲nzen und Banknoten.","Ein Beh칛ltnis f칲r Bargeld und oft auch Kreditkarten."],"examples":["Ich habe mein Portemonnaie verloren.","Das Portemonnaie ist aus Leder.","Sie hat ihr Portemonnaie in der Tasche."],"lemma":"Portemonnaie","lemmaPos":"noun","synonyms":["Geldbeutel","Geldb칬rse","Brieftasche"],"number":"singular","pluralForm":"die Portemonnaies","gender":"neuter","source":"das Portemonnaie"}