{"transcript":"lokaliˈziːʁən","exists":true,"definitions":["Den Ort oder die Position von etwas bestimmen.","Sich an einem bestimmten Ort ansiedeln oder befinden.","Auf einen bestimmten Ort beschränken."],"examples":["Wir müssen die Fehlerquelle lokalisieren.","Das Problem lässt sich schwer lokalisieren.","Die Schmerzen lokalisieren sich im Rücken."],"lemma":"lokalisieren","lemmaPos":"verb","synonyms":["orten","auffinden","feststellen"],"number":"singular","tense":"present","pastTenses":"lokalisierte, hat lokalisiert","presentTenses":"ich lokalisiere, du lokalisierst, er/sie/es lokalisiert","isIrregular":false,"source":"lokalisieren"}