{"transcript":"ˈʃalˌdɛmpfɐ","exists":true,"definitions":["Vorrichtung zur Verringerung von Schallemissionen bei Maschinen oder Schusswaffen.","Bauteil in Abgasanlagen von Kraftfahrzeugen zur Lärmreduzierung."],"examples":["Der Schalldämpfer am Auto ist defekt.","Er schraubte den Schalldämpfer auf den Lauf.","Ein neuer Schalldämpfer reduziert den Lärm."],"lemma":"Schalldämpfer","lemmaPos":"noun","synonyms":["Auspufftopf","Dämpfer","Absorber"],"number":"singular","pluralForm":"die Schalldämpfer","gender":"masculine","source":"Schalldämpfer"}