{"transcript":"ˈʀaʊ̯sˌbʀɪŋən","exists":true,"definitions":["etwas nach draußen bringen","etwas veröffentlichen (z.B. ein Buch, eine CD)","jemanden aus einer schwierigen Lage befreien"],"examples":["Er muss den Müll rausbringen.","Die Band wird bald ein neues Album rausbringen.","Wir müssen ihn aus dieser Situation rausbringen."],"lemma":"rausbringen","lemmaPos":"verb","synonyms":["herausbringen","veröffentlichen","retten"],"number":"singular","pastTenses":"brachte raus, hat rausgebracht","tense":"present","source":"rausbringen"}