{"transcript":"ˈflakɐn","exists":true,"definitions":["Unruhig, zitternd brennen oder leuchten","Sich schnell und unregelmäßig bewegen oder hin- und herbewegen"],"examples":["Die Kerze flackert im Wind.","Das Licht flackert kurz auf.","Ihre Augen flackerten vor Wut."],"lemma":"flackern","lemmaPos":"verb","synonyms":["flimmern","lodern","zucken","wabern"],"number":"singular","tense":"present","pastTenses":"flackerte, hat geflackert","presentTenses":"ich flackere, du flackerst, er/sie/es flackert","isIrregular":false,"source":"flackern"}