{"transcript":"틛zaxb톛틟툾a투ba톩퍒t톛투톩n","exists":true,"definitions":["Eine weibliche Person, die in einem B칲ro oder einer Verwaltung bestimmte Aufgaben und Vorg칛nge bearbeitet.","Angestellte, die f칲r die Bearbeitung spezifischer Sachverhalte zust칛ndig ist."],"examples":["Die Sachbearbeiterin pr칲ft die Unterlagen.","Unsere neue Sachbearbeiterin ist sehr kompetent.","Fragen Sie bitte die Sachbearbeiterin in Zimmer 203."],"lemma":"Sachbearbeiterin","lemmaPos":"noun","synonyms":["B칲rokraft","Verwaltungsangestellte","Referentin"],"number":"singular","pluralForm":"die Sachbearbeiterinnen","gender":"feminine","source":"Sachbearbeiterin"}