{"transcript":"nɪçts ˈmaxn̩","exists":true,"definitions":["Untätig sein","Sich nicht rühren","Keine Handlung vornehmen","Sich nicht einmischen"],"examples":["Er wird den ganzen Tag nichts machen.","Warum hast du nichts gemacht?","Sie können nichts machen, um das zu ändern."],"lemma":"nichts machen","lemmaPos":"verb","synonyms":["untätig sein","faulenzen","herumsitzen"],"number":"other","tense":"other","pastTenses":"hat nichts gemacht, hatte nichts gemacht","presentTenses":"ich mache nichts, du machst nichts, er/sie/es macht nichts","isIrregular":false,"source":"nichts machen"}