{"transcript":"ɡəˈvʏʁt͡sˌhandl̩","exists":true,"definitions":["Der Handel mit Gewürzen.","Die Branche, die sich mit dem Import, Export und Verkauf von Gewürzen befasst."],"examples":["Der Gewürzhandel florierte im Mittelalter.","Ein wichtiger Aspekt des Gewürzhandels ist die Qualitätssicherung.","Er stieg in den Gewürzhandel ein."],"lemma":"Gewürzhandel","lemmaPos":"noun","synonyms":["Gewürzgeschäft","Gewürzmarkt"],"number":"singular","pluralForm":"die Gewürzhändel","gender":"masculine","source":"der Gewürzhandel"}