{"transcript":"d…õ…źŐĮ ňąanfaŇč f…Ēm ňą…õnd…ô","exists":true,"definitions":["Der Beginn eines Prozesses, der unweigerlich zum Untergang oder zur Beendigung von etwas f√ľhrt.","Der erste Schritt in einer Entwicklung, die zu einem negativen oder finalen Ergebnis f√ľhrt."],"examples":["Mit dem ersten Fehler war es der Anfang vom Ende seiner Karriere.","Die Schlie√üung der Filiale war der Anfang vom Ende des Unternehmens.","F√ľr viele war die neue Regelung der Anfang vom Ende der alten Traditionen."],"lemma":"der Anfang vom Ende","lemmaPos":"idiom","synonyms":["der Anfang vom Untergang","der erste Schritt zum Verfall"],"number":"singular","gender":"masculine","source":"der Anfang vom Ende"}