{"transcript":"fɛɐˈliːən","exists":true,"definitions":["jemandem etwas offiziell geben, zuteilen (z.B. einen Preis, Titel)","etwas für eine bestimmte Zeit zur Nutzung überlassen (z.B. ein Buch, Werkzeug)"],"examples":["Der Preis wurde ihm verliehen.","Sie hat das Buch verliehen.","Ihm wurde ein Orden verliehen."],"lemma":"verleihen","lemmaPos":"verb","synonyms":["geben","zuerkennen","übertragen","leihen"],"number":"other","tense":"past","pastTenses":"hat verliehen, hatte verliehen","presentTenses":"ich verleihe, du verleihst, er/sie/es verleiht","isIrregular":true,"source":"verliehen"}