{"transcript":"ﾋ坰oﾋ惜昔ｯbﾉ厖弧‖ﾉｪﾌｯtﾉ冲","exists":true,"definitions":["hat etwas fﾃｼr die Zukunft geplant oder arrangiert","ist bereit oder bereit gemacht worden","hat sich auf etwas eingestellt"],"examples":["Er hat die Prﾃ､sentation gut vorbereitet.","Die Studenten sind auf die Prﾃｼfung vorbereitet.","Sie hat das Essen fﾃｼr die Gﾃ､ste vorbereitet."],"lemma":"vorbereiten","lemmaPos":"verb","synonyms":["planen","arrangieren","rﾃｼsten"],"number":"singular","tense":"past","pastTenses":"hat vorbereitet, hatte vorbereitet","presentTenses":"ich bereite vor, du bereitest vor, er/sie/es bereitet vor","isIrregular":false,"source":"vorbereitet"}