{"transcript":"ﾋ位穫voﾋ人ﾋ掲yﾋ人ﾉ冢","exists":true,"definitions":["Sich nicht gut fﾃｼhlen, kﾃｶrperlich oder seelisch","Ein Gefﾃｼhl des Unbehagens oder der Krankheit haben"],"examples":["Ich fange an, mich unwohlzufﾃｼhlen.","Sie fﾃｼhlte sich plﾃｶtzlich unwohl.","Er wird sich unwohlfﾃｼhlen, wenn er das hﾃｶrt."],"lemma":"unwohlfﾃｼhlen","lemmaPos":"verb","synonyms":["krank fﾃｼhlen","ﾃｼbel sein","sich nicht wohlfﾃｼhlen"],"number":"singular","tense":"present","pastTenses":"fﾃｼhlte sich unwohl, hat sich unwohlgefﾃｼhlt","presentTenses":"ich fﾃｼhle mich unwohl, du fﾃｼhlst dich unwohl, er/sie/es fﾃｼhlt sich unwohl","isIrregular":false,"source":"unwohlfﾃｼhlen"}