{"transcript":"proˈt͡sɛs","exists":true,"definitions":["Ein gerichtliches Verfahren zur Entscheidung über Rechtsstreitigkeiten.","Ein Verlauf oder eine Abfolge von Ereignissen oder Zuständen.","Ein in Ausführung befindliches Programm in der Informatik."],"examples":["Der Prozess beginnt morgen.","Ein biologischer Prozess.","Der chemische Prozess läuft ab."],"lemma":"Prozess","lemmaPos":"noun","synonyms":["Verfahren","Ablauf","Vorgang","Rechtsstreit"],"number":"singular","pluralForm":"die Prozesse","gender":"masculine","source":"Prozess"}