{"transcript":"톝톓퍒틛la툵퍒b톛","exists":true,"definitions":["Ich erlaube etwas, jemandem etwas zu tun.","Ich gebe die Erlaubnis f칲r etwas."],"examples":["Ich erlaube dir, zu gehen.","Erlaube mir, mich vorzustellen.","Ich erlaube keine Ausnahmen."],"lemma":"erlauben","lemmaPos":"verb","synonyms":["gestatten","zulassen","genehmigen"],"number":"singular","tense":"present","pastTenses":"erlaubte, hat erlaubt","presentTenses":"ich erlaube, du erlaubst, er/sie/es erlaubt","isIrregular":false,"source":"erlaube"}