{"transcript":"bəˈveːɡn̩","exists":true,"definitions":["etwas von einem Ort zum anderen bringen","sich fortbewegen","jemanden emotional berühren","etwas in Gang setzen"],"examples":["Er bewegt den Stuhl.","Das Auto bewegt sich schnell.","Ihre Geschichte hat mich sehr bewegt.","Die Ereignisse bewegen die Gemüter."],"lemma":"bewegen","lemmaPos":"verb","synonyms":["rühren","verschieben","fortbewegen","berühren"],"number":"singular","pastTenses":"bewegte, hat bewegt (weak); bewog, hat bewogen (strong)","tense":"present","source":"bewegen"}