{"transcript":"ˈɡaːbl̩n","exists":true,"definitions":["mit einer Gabel aufnehmen","sich verzweigen, sich teilen (umgangssprachlich)","etwas mit einer Gabel stechen"],"examples":["Er gabelt das Fleisch auf.","Der Weg gabelt sich hier.","Sie gabelte die Kartoffel."],"lemma":"gabeln","lemmaPos":"verb","synonyms":["aufspießen","teilen","verzweigen"],"number":"plural","tense":"present","pastTenses":"gabelte, hat gegabelt","presentTenses":"ich gabel, du gabelst, er/sie/es gabelt","isIrregular":false,"source":"gabeln"}