{"transcript":"ﾋ𡈽pﾋ系ﾊ閣ﾍ｡snﾌｩ","exists":true,"definitions":["durch Gebrauch oder Reibung verschleiﾃ歹n","durch hﾃ､ufigen Gebrauch unbrauchbar machen","an Wert oder Funktion verlieren"],"examples":["Die Reifen nutzen sich schnell ab.","Das Material nutzt sich mit der Zeit ab.","Seine Kleidung nutzt sich rasch ab."],"lemma":"abnutzen","lemmaPos":"verb","synonyms":["verschleiﾃ歹n","abtragen","verbrauchen"],"number":"singular","pastTenses":"nutzte ab, hat abgenutzt","tense":"present","source":"abnutzen"}