{"transcript":"apozioˈpeːzə","exists":true,"definitions":["Rhetorische Figur, bei der ein Satz oder Gedanke absichtlich unvollendet bleibt.","Abrupter Abbruch eines Satzes, oft um Spannung zu erzeugen oder eine Emotion auszudrücken."],"examples":["„Wenn ich nur wüsste, was…“","„Ich könnte dir jetzt sagen, aber…“","Die Aposiopese in seiner Rede war sehr wirkungsvoll."],"lemma":"Aposiopese","lemmaPos":"noun","synonyms":["Satzabbruch","Gedankenabbruch"],"number":"singular","pluralForm":"die Aposiopesen","gender":"feminine","source":"Aposiopese"}