{"transcript":"藞an藢伞a藧b蓹","exists":true,"definitions":["Information oder Auskunft 眉ber einen Sachverhalt","Anweisung oder Vorgabe","Aufschlag beim Sport (z. B. Tennis oder Volleyball)","Prahlerisches Verhalten"],"examples":["Die Angabe der Adresse fehlt.","Genaue Angaben machen.","Eine starke Angabe beim Tennis.","H枚r auf mit der Angabe!"],"lemma":"Angabe","lemmaPos":"noun","synonyms":["Information","Auskunft","Daten","Aufschlag","Prahlerei"],"number":"singular","pluralForm":"die Angaben","gender":"feminine","source":"Angabe"}