{"transcript":"ˈʃveːptə","exists":true,"definitions":["bewegte sich in der Luft oder auf dem Wasser, ohne den Boden zu berühren","war in einem Zustand der Unsicherheit oder Unentschlossenheit","war in Gefahr oder drohte zu passieren"],"examples":["Der Ballon schwebte sanft über die Wiesen.","Eine unheimliche Stille schwebte im Raum.","Sein Leben schwebte in großer Gefahr."],"lemma":"schweben","lemmaPos":"verb","synonyms":["gleiten","fliegen","treiben"],"number":"singular","pastTenses":"schwebte, ist geschwebt","tense":"past","source":"schwebte"}