{"transcript":"ﾋ埿raﾋ震ﾋ掲ﾉ嵳震ﾉｪﾃｧkaﾉｪt","exists":true,"definitions":["Die Fﾃ､higkeit eines Materials oder einer Struktur, eine Last zu tragen.","Das maximale Gewicht, das ein Fahrzeug, ein Gebﾃ､ude oder eine andere Struktur sicher tragen kann.","Die Kapazitﾃ､t eines ﾃ北osystems, eine bestimmte Anzahl von Individuen einer Art zu unterstﾃｼtzen."],"examples":["Die Tragfﾃ､higkeit der Brﾃｼcke wurde getestet.","Die Tragfﾃ､higkeit des Bodens ist entscheidend fﾃｼr den Bau.","Die Tragfﾃ､higkeit des Schiffes ist begrenzt."],"lemma":"Tragfﾃ､higkeit","lemmaPos":"noun","synonyms":["Belastbarkeit","Ladekapazitﾃ､t","Kapazitﾃ､t"],"number":"singular","pluralForm":"die Tragfﾃ､higkeiten","gender":"feminine","source":"Tragfﾃ､higkeit"}