{"transcript":"de틣톓퍒 틛l톩칞t틟툮a톩퍒n","exists":true,"definitions":["Heller Schein, der von einer Lichtquelle ausgeht.","Das sichtbare Licht, das von etwas reflektiert oder ausgestrahlt wird."],"examples":["Der Lichtschein der Kerze tanzte an der Wand.","Ein schwacher Lichtschein drang durch die Ritzen der T칲r.","Im Lichtschein des Mondes wirkte alles mysteri칬s."],"lemma":"Lichtschein","lemmaPos":"noun","synonyms":["Schein","Lichtglanz","Lichtschimmer"],"number":"singular","pluralForm":"die Lichtscheine","gender":"masculine","source":"Lichtschein"}