{"transcript":"ɛɐ̯ˈɡiːsn̩","exists":true,"definitions":["sich ergießen: sich in großer Menge ausbreiten, fließen","sich ergießen: sich über jemanden oder etwas ergießen (oft im übertragenen Sinne, z.B. Schimpfwörter)"],"examples":["Der Fluss ergießt sich ins Meer.","Die Lava ergießt sich den Hang hinunter.","Schimpfwörter ergossen sich über ihn."],"lemma":"ergießen","lemmaPos":"verb","synonyms":["fließen","strömen","ausbreiten"],"number":"singular","pastTenses":"ergoss sich, hat sich ergossen","tense":"present","source":"ergießen"}