{"transcript":"diː ˈst͡seːnə","exists":true,"definitions":["Ein Ort, an dem sich etwas ereignet oder abspielt.","Ein Abschnitt in einem Theaterstück, Film oder Oper.","Eine Gruppe von Menschen mit gemeinsamen Interessen oder einem bestimmten Lebensstil."],"examples":["Die Szene war voller Spannung.","Er betrat die Szene.","Die Berliner Szene ist sehr lebendig."],"lemma":"Szene","lemmaPos":"noun","synonyms":["Schauplatz","Akt","Milieu"],"number":"singular","pluralForm":"die Szenen","gender":"feminine","source":"die Szene"}