{"transcript":"틛e틣톓퍒l톩칞ka톩퍒t포s틟t톝st","exists":true,"definitions":["Ein Test, der die Ehrlichkeit einer Person 칲berpr칲ft.","Eine Methode zur Bewertung der Aufrichtigkeit oder Redlichkeit."],"examples":["Der Bewerber musste einen Ehrlichkeitstest bestehen.","Viele Unternehmen nutzen Ehrlichkeitstests.","Der Ehrlichkeitstest ergab keine Auff칛lligkeiten."],"lemma":"Ehrlichkeitstest","lemmaPos":"noun","synonyms":["Integrit칛tstest","Redlichkeitstest"],"number":"singular","pluralForm":"die Ehrlichkeitstests","gender":"masculine","source":"Ehrlichkeitstest"}