{"transcript":"pʁostituˈt͡si̯oːn","exists":true,"definitions":["Gewerbsmäßige Ausübung sexueller Handlungen gegen Bezahlung.","Herabwürdigung oder Verkauf der eigenen Überzeugungen oder Talente für materielle Vorteile."],"examples":["Die Prostitution ist gesetzlich geregelt.","Sie wehrte sich gegen die Prostitution ihrer Kunst."],"lemma":"Prostitution","lemmaPos":"noun","synonyms":["Gewerbe","Käuflichkeit","Sexarbeit"],"number":"singular","pluralForm":"die Prostitutionen","gender":"feminine","source":"Prostitution"}