{"transcript":"ˈraɪ̯ə","exists":true,"definitions":["Eine Anzahl von Personen oder Dingen, die in einer Linie nebeneinander oder hintereinander aufgestellt sind.","Eine zeitliche Abfolge von Ereignissen oder Objekten.","Eine mathematische Summe von Gliedern einer Folge."],"examples":["In der ersten Reihe sitzen.","Eine Reihe von Fehlern.","Wer ist an der Reihe?","Aus der Reihe tanzen."],"lemma":"Reihe","lemmaPos":"noun","synonyms":["Serie","Folge","Linie","Kette","Abfolge"],"number":"singular","pluralForm":"die Reihen","gender":"feminine","source":"Reihe"}