{"transcript":"ˈapˌvɛksl̩n","exists":true,"definitions":["sich mit jemandem oder etwas abwechseln","etwas abwechselnd tun","sich ändern, variieren"],"examples":["Wir abwechseln uns bei der Arbeit.","Sie abwechseln die Farben.","Das Wetter abwechselt ständig."],"lemma":"abwechseln","lemmaPos":"verb","synonyms":["wechseln","variieren","rotieren"],"number":"singular","tense":"present","pastTenses":"wechselte ab, hat abgewechselt","presentTenses":"ich wechsle ab, du wechselst ab, er/sie/es wechselt ab","isIrregular":false,"source":"abwechseln"}