{"transcript":"fɛɐ̯ˈlast","exists":true,"definitions":["Ihr geht weg von einem Ort.","Ihr lasst jemanden oder etwas zurück.","Ihr gebt etwas auf oder beendet es."],"examples":["Ihr verlasst das Gebäude jetzt.","Verlasst euch nicht auf andere.","Warum verlasst ihr die Party so früh?"],"lemma":"verlassen","lemmaPos":"verb","synonyms":["weggehen","aufgeben","zurücklassen"],"number":"plural","tense":"present","pastTenses":"verließ, hat verlassen","presentTenses":"ich verlasse, du verlässt, er/sie/es verlässt","isIrregular":true,"source":"verlasst"}