{"transcript":"ʃpekuliːʁən","exists":true,"definitions":["Vermutungen über zukünftige Ereignisse anstellen","Finanzielle Geschäfte mit der Erwartung auf Gewinn tätigen","Über etwas nachdenken, überlegen"],"examples":["Er spekuliert auf steigende Aktienkurse.","Man kann nur spekulieren, was passieren wird.","Sie spekulierte über den Ausgang des Spiels."],"lemma":"spekulieren","lemmaPos":"verb","synonyms":["mutmaßen","vermuten","wetten","nachdenken"],"number":"singular","pastTenses":"spekulierte, hat spekuliert","tense":"present","source":"spekulieren"}