{"transcript":"bəˈvaɪ̯st","exists":true,"definitions":["zeigt die Wahrheit oder Richtigkeit von etwas","erbringt den Beweis für etwas","macht etwas offensichtlich oder klar"],"examples":["Er beweist seine Unschuld.","Das Experiment beweist die Theorie.","Die Fakten beweisen seine Behauptung."],"lemma":"beweisen","lemmaPos":"verb","synonyms":["belegen","nachweisen","darlegen","bestätigen"],"number":"singular","tense":"present","pastTenses":"bewies, hat bewiesen","presentTenses":"ich beweise, du beweist, er/sie/es beweist","isIrregular":true,"source":"beweist"}