{"transcript":"ˈanˌmiːtn̩","exists":true,"definitions":["etwas für eine bestimmte Zeit gegen Bezahlung mieten","einen Mietvertrag für etwas abschließen"],"examples":["Wir wollen ein Haus anmieten.","Sie hat ein Auto angemietet.","Die Firma mietet Büroräume an."],"lemma":"anmieten","lemmaPos":"verb","synonyms":["mieten","pachten","leasen"],"number":"singular","tense":"present","pastTenses":"mietete an, hat angemietet","presentTenses":"ich miete an, du mietest an, er/sie/es mietet an","isIrregular":false,"source":"anmieten"}