{"transcript":"bəˈzɛt͡sn̩","exists":true,"definitions":["Einen Platz, eine Stelle oder ein Amt einnehmen oder füllen.","Ein Gebiet militärisch einnehmen und kontrollieren.","Eine Rolle in einem Film oder Theaterstück vergeben.","Einen Raum oder ein Gebäude in Besitz nehmen, oft widerrechtlich."],"examples":["Die Demonstranten besetzen das Gebäude.","Er besetzt die Position des Direktors.","Der Regisseur besetzt die Hauptrolle neu.","Die Truppen besetzen die Stadt."],"lemma":"besetzen","lemmaPos":"verb","synonyms":["einnehmen","belegen","füllen","okkupieren"],"number":"plural","pastTenses":"besetzte, hat besetzt","tense":"present","source":"besetzen"}