{"transcript":"ˈʁɔlə","exists":true,"definitions":["Ein zylindrischer Gegenstand, um den etwas gewickelt ist.","Die Aufgabe oder Figur, die jemand in einem Film oder Theaterstück verkörpert.","Eine kreisförmige Bewegung des Körpers um die Querachse.","Ein kleines Rad unter Möbeln oder Geräten."],"examples":["Eine Rolle Klopapier.","Sie spielt die Hauptrolle.","Vorwärtsrolle im Sportunterricht.","Die Rollen am Bürostuhl."],"lemma":"Rolle","lemmaPos":"noun","synonyms":["Walze","Spule","Partie","Funktion"],"number":"singular","pluralForm":"die Rollen","gender":"feminine","source":"Rolle"}