{"transcript":"lo.ka.li.ˈziːɐ̯t","exists":true,"definitions":["befindet sich an einem bestimmten Ort","wurde an einem bestimmten Ort gefunden oder identifiziert","auf einen bestimmten Ort beschränkt"],"examples":["Der Fehler ist im System lokalisiert.","Die Schmerzquelle wurde lokalisiert.","Das Problem ist auf diese Abteilung lokalisiert."],"lemma":"lokalisieren","lemmaPos":"verb","synonyms":["orten","auffinden","eingrenzen"],"number":"singular","tense":"present","pastTenses":"hat lokalisiert, hatte lokalisiert","presentTenses":"ich lokalisiere, du lokalisierst, er/sie/es lokalisiert","isIrregular":false,"source":"lokalisiert"}