{"transcript":"kﾊ穫dﾉ冢ﾋ茎ﾉ嵋昔ｯvﾉｪs","exists":true,"definitions":["Abteilung oder Dienstleistung, die sich um die Anliegen und Probleme von Kunden kﾃｼmmert.","Gesamtheit der Maﾃ殤ahmen, die ein Unternehmen ergreift, um die Zufriedenheit seiner Kunden sicherzustellen."],"examples":["Der Kundenservice ist telefonisch erreichbar.","Ein guter Kundenservice ist entscheidend fﾃｼr den Erfolg.","Ich habe eine Beschwerde an den Kundenservice geschickt."],"lemma":"Kundenservice","lemmaPos":"noun","synonyms":["Kundenbetreuung","Kundenberatung","Support"],"number":"singular","pluralForm":"die Kundenservices","gender":"masculine","source":"der Kundenservice"}