{"transcript":"ˈbyːʁoːɡəˌbɔʏdə","exists":true,"definitions":["Ein Gebäude, das hauptsächlich für Büros genutzt wird.","Ein Bauwerk, in dem Unternehmen oder Organisationen ihre Geschäftsräume haben."],"examples":["Das neue Bürogebäude hat viele Mieter.","Wir arbeiten in einem modernen Bürogebäude.","Der Bau des Bürogebäude dauerte zwei Jahre."],"lemma":"Bürogebäude","lemmaPos":"noun","synonyms":["Bürohaus","Geschäftshaus","Verwaltungsgebäude"],"number":"singular","pluralForm":"die Bürogebäude","gender":"neuter","source":"Bürogebäude"}