{"transcript":"faˈmiːli̯ə","exists":true,"definitions":["Eine soziale Gruppe, die meist aus Eltern und Kindern besteht.","Eine Gruppe von Personen, die miteinander verwandt sind.","In der Biologie eine hierarchische Ebene der Klassifikation."],"examples":["Meine Familie lebt in Berlin.","Sie hat eine große Familie.","Die Familie hält zusammen."],"lemma":"Familie","lemmaPos":"noun","synonyms":["Sippe","Angehörige","Haus","Verwandtschaft"],"number":"singular","pluralForm":"die Familien","gender":"feminine","source":"Familie"}