{"transcript":"ˈtaʊ̯fə","exists":true,"definitions":["Feierliche Aufnahme einer Person in die christliche Gemeinschaft durch Übergießen mit Wasser.","Namensgebung bei einem Schiff oder einem neuen Projekt."],"examples":["Die Taufe findet am Sonntag statt.","Nach der Taufe gab es ein Fest.","Die Taufe des neuen Kreuzfahrtschiffs."],"lemma":"Taufe","lemmaPos":"noun","synonyms":["Christening","Namensgebung","Initiation"],"number":"singular","pluralForm":"die Taufen","gender":"feminine","source":"Taufe"}