{"exists":true,"definitions":["Eine Person, die am Straßenverkehr teilnimmt, sei es als Fahrer, Beifahrer, Fußgänger oder Radfahrer.","Jemand, der sich im öffentlichen Verkehrsraum bewegt."],"examples":["Jeder Verkehrsteilnehmer muss die Regeln beachten.","Die Sicherheit der Verkehrsteilnehmer hat oberste Priorität.","Rücksichtsvolle Verkehrsteilnehmer tragen zur Flüssigkeit des Verkehrs bei."],"lemma":"Verkehrsteilnehmer","lemmaPos":"noun","synonyms":["Straßennutzer","Verkehrsbeteiligter"],"number":"singular","pluralForm":"die Verkehrsteilnehmer","gender":"masculine","source":"Verkehrsteilnehmer","transcript":""}