{"transcript":"ňąyňźb…źňĆt Ā…õfnŐ©","exists":true,"definitions":["besser sein als jemand oder etwas anderes","in Leistung oder Qualit√§t √ľberlegen sein","die Erwartungen √ľbersteigen"],"examples":["Er konnte alle Erwartungen √ľbertreffen.","Ihre Leistung wird die vorherige √ľbertreffen.","Das neue Modell soll das alte in jeder Hinsicht √ľbertreffen."],"lemma":"√ľbertreffen","lemmaPos":"verb","synonyms":["√ľberbieten","√ľberragen","√ľbersteigen","toppen"],"number":"plural","tense":"present","pastTenses":"√ľbertraf, hat √ľbertroffen","presentTenses":"ich √ľbertreffe, du √ľbertriffst, er/sie/es √ľbertrifft","isIrregular":true,"source":"√ľbertreffen"}