{"transcript":"ɡəˈkɛmpft","exists":true,"definitions":["Sich in einem Kampf oder Wettstreit befinden","Sich mit Anstrengung für etwas einsetzen","Eine Auseinandersetzung mit jemandem haben"],"examples":["Sie haben tapfer gekämpft.","Er hat um sein Leben gekämpft.","Wir haben lange gegen die Ungerechtigkeit gekämpft."],"lemma":"kämpfen","lemmaPos":"verb","synonyms":["streiten","ringen","fechten","sich schlagen"],"number":"other","tense":"past","pastTenses":"kämpfte, hat gekämpft","presentTenses":"ich kämpfe, du kämpfst, er/sie/es kämpft","isIrregular":false,"source":"gekämpft"}