{"transcript":"ˈanˌkaʊ̯fn̩","exists":true,"definitions":["etwas erwerben, kaufen, besonders in größeren Mengen oder für einen bestimmten Zweck","etwas in Besitz nehmen durch Kauf"],"examples":["Wir wollen Gold ankaufen.","Die Firma wird Immobilien ankaufen.","Er hat alte Münzen angekauft."],"lemma":"ankaufen","lemmaPos":"verb","synonyms":["erwerben","kaufen","einkaufen"],"number":"singular","tense":"present","pastTenses":"kaufte an, hat angekauft","presentTenses":"ich kaufe an, du kaufst an, er/sie/es kauft an","isIrregular":false,"source":"ankaufen"}