{"transcript":"ˈbʁʏkə","exists":true,"definitions":["Bauwerk zur Überquerung von Hindernissen","Verbindung zwischen zwei Dingen","Teil eines Schiffes zur Steuerung","Zahnersatz zur Überbrückung einer Lücke"],"examples":["Die Brücke führt über den Fluss.","Er schlägt eine Brücke zwischen den Kulturen.","Der Kapitän steht auf der Brücke.","Der Zahnarzt setzt eine Brücke ein."],"lemma":"Brücke","lemmaPos":"noun","synonyms":["Viadukt","Steg","Verbindung","Übergang"],"number":"singular","pluralForm":"die Brücken","gender":"feminine","source":"Brücke"}