{"transcript":"ˈanklamɐn","exists":true,"definitions":["sich an etwas festhalten","sich an jemanden klammern","sich an etwas klammern, um Halt zu finden"],"examples":["Er klammerte sich an den Ast.","Sie klammerte sich an ihre Mutter.","Das Kind klammerte sich an sein Kuscheltier."],"lemma":"anklammern","lemmaPos":"verb","synonyms":["festhalten","klammern","anhängen"],"number":"singular","tense":"present","pastTenses":"klammerte an, hat angeklammert","presentTenses":"ich klammere an, du klammerst an, er/sie/es klammert an","isIrregular":false,"source":"anklammern"}