{"transcript":"ňąmiňźm…™k","exists":true,"definitions":["Gesichtsausdruck als Mittel der nonverbalen Kommunikation","Gesamtheit der Bewegungen der Gesichtsmuskeln"],"examples":["Ihre Mimik verriet ihre √úberraschung.","Die Mimik des Schauspielers war sehr ausdrucksstark.","Er studierte die Mimik seiner Gespr√§chspartner."],"lemma":"Mimik","lemmaPos":"noun","synonyms":["Gesichtsausdruck","Mienenspiel","Physiognomie"],"number":"singular","pluralForm":"die Mimiken","gender":"feminine","source":"die Mimik"}