{"transcript":"demoˈliːɐ̯t ˈvɛʁdn̩","exists":true,"definitions":["Völlig zerstört oder beschädigt werden.","Umgangssprachlich: Stark betrunken sein.","Umgangssprachlich: Eine Niederlage erleiden, geschlagen werden."],"examples":["Das alte Gebäude wird demoliert werden.","Nach der Party war er völlig demoliert werden.","Unsere Mannschaft wird demoliert werden, wenn wir so spielen."],"lemma":"demoliert werden","lemmaPos":"verb phrase","synonyms":["zertrümmert werden","kaputtgemacht werden","zerschlagen werden"],"number":"other","source":"demoliert werden"}