{"transcript":"fɔlˈʔɛndʊŋ","exists":true,"definitions":["Der Abschluss oder die Fertigstellung eines Werkes oder einer Handlung.","Der Zustand höchster Vollkommenheit oder Meisterschaft."],"examples":["Die Vollendung des Bauprojekts.","Ein Kunstwerk von höchster Vollendung.","Kurz vor der Vollendung stehen."],"lemma":"Vollendung","lemmaPos":"noun","synonyms":["Abschluss","Fertigstellung","Vollkommenheit","Perfektion"],"number":"singular","pluralForm":"die Vollendungen","gender":"feminine","source":"Vollendung"}