{"transcript":"ɛɐ̯ˈt͡soːɡn̩","exists":true,"definitions":["jemanden durch Erziehung zu einem bestimmten Verhalten oder Charakter formen","jemandem bestimmte Werte oder Fähigkeiten durch Erziehung vermitteln"],"examples":["Sie hat ihre Kinder gut erzogen.","Er wurde streng erzogen.","Die Kinder sind höflich erzogen worden."],"lemma":"erziehen","lemmaPos":"verb","synonyms":["bilden","schulen","unterrichten","ausbilden"],"number":"other","tense":"past","pastTenses":"erzog, hat erzogen","presentTenses":"ich erziehe, du erziehst, er/sie/es erzieht","isIrregular":true,"source":"erzogen"}