{"transcript":"lohn","exists":true,"definitions":["Der Lohn ist die Bezahlung für geleistete Arbeit.","Der Lohn ist die Belohnung für Mühe oder Anstrengung."],"examples":["Der Lohn für die harte Arbeit war hoch.","Sein Lohn wurde pünktlich ausgezahlt."],"lemma":"lohnen","lemmaPos":"verb","synonyms":["vergüten","entgelten","bezahlen"],"number":"singular","tense":"present","pastTenses":"lohnte, hat gelohnt","presentTenses":"ich lohne, du lohnst, er/sie/es lohnt","isIrregular":false,"source":"lohn"}