{"exists":true,"definitions":["Die Kontrolle über eine Situation oder eine große Menge an Informationen behalten.","Sich in einer komplexen Lage zurechtfinden und das Wesentliche nicht aus den Augen verlieren.","Eine klare Vorstellung von der Gesamtsituation haben."],"examples":["Es ist wichtig, bei so vielen Aufgaben den Überblick zu behalten.","Trotz des Chaos konnte sie den Überblick behalten.","Um den Überblick zu behalten, notierte er sich alles Wichtige."],"lemma":"den Überblick behalten","lemmaPos":"idiom","synonyms":["alles im Griff haben","die Fäden in der Hand halten","sich zurechtfinden"],"number":"singular","source":"den Überblick behalten","transcript":""}