{"transcript":"b…ôΥà ¹ èkz…ΣΟßt…ΣΟßt","exists":true,"definitions":["Nimmt etwas in Betracht oder zieht es in ErwΟΛgung.","Beachtet etwas oder trΟΛgt ihm Rechnung.","Hat etwas bedacht oder miteinbezogen."],"examples":["Er hat alle Aspekte berΟΦcksichtigt.","Die neue Regelung berΟΦcksichtigt die BedΟΦrfnisse aller.","Wurde das Feedback berΟΦcksichtigt?"],"lemma":"berΟΦcksichtigen","lemmaPos":"verb","synonyms":["beachten","einbeziehen","bedenken","erwΟΛgen"],"number":"singular","tense":"present","pastTenses":"berΟΦcksichtigte, hat berΟΦcksichtigt","presentTenses":"ich berΟΦcksichtige, du berΟΦcksichtigst, er/sie/es berΟΦcksichtigt","isIrregular":false,"source":"berΟΦcksichtigt"}