{"transcript":"ˈkɛnt͡saɪ̯çn̩","exists":true,"definitions":["Ein Merkmal, an dem man jemanden oder etwas erkennt.","Ein Schild an Fahrzeugen mit einer Buchstaben-Zahlen-Kombination.","Ein Zeichen oder Symbol zur Identifizierung."],"examples":["Das Kennzeichen des Autos.","Ein typisches Kennzeichen der Krankheit.","Das Kennzeichen fehlt."],"lemma":"Kennzeichen","lemmaPos":"noun","synonyms":["Merkmal","Nummernschild","Charakteristikum","Anzeichen"],"number":"singular","pluralForm":"die Kennzeichen","gender":"neuter","source":"Kennzeichen"}